ExpSmoothing/__init__.py
ExpSmoothing/model.py
ExpSmoothing-0.1.9.dist-info/LICENSE
ExpSmoothing-0.1.9.dist-info/METADATA
ExpSmoothing-0.1.9.dist-info/WHEEL
ExpSmoothing-0.1.9.dist-info/top_level.txt
ExpSmoothing-0.1.9.dist-info/RECORD
